{
  "naics": "332216",
  "title": "Saw Blade and Handtool Manufacturing",
  "labor_share": {
    "value": 0.2381,
    "method": "QCEW 2024 private total annual wages at 332216 ($1,783,305,725) x benefits multiplier 1.4294 [ECEC private-industry total comp $46.60/hr / wages $32.60/hr = 1.4294 (March 2026 reference period)] / SUSB 2022 receipts at 332216 ($7,985,696,000). Vintage mismatch: 2024 wages over 2022 receipts, stated. Level: 6-digit. Harmonized to IPS basis \u00f71.3407 (median of 65 dual-method codes).",
    "sources": [
      "BLS QCEW 2024 annual averages (US000, private)",
      "BLS ECEC news release (raw/ecec.nr0.htm)",
      "Census SUSB 2022 (receipts by NAICS)"
    ],
    "year": "2024 wages / 2022 receipts",
    "quality": "MED"
  },
  "role_mix": {
    "oews_level": "3-digit 332",
    "occupations": [
      {
        "soc": "51-2090",
        "title": "Miscellaneous Assemblers and Fabricators",
        "emp_share": 0.0851,
        "wage_share": 0.062
      },
      {
        "soc": "51-4121",
        "title": "Welders, Cutters, Solderers, and Brazers",
        "emp_share": 0.077,
        "wage_share": 0.0661
      },
      {
        "soc": "51-4041",
        "title": "Machinists",
        "emp_share": 0.0703,
        "wage_share": 0.0629
      },
      {
        "soc": "51-1011",
        "title": "First-Line Supervisors of Production and Operating Workers",
        "emp_share": 0.0477,
        "wage_share": 0.0575
      },
      {
        "soc": "51-9161",
        "title": "Computer Numerically Controlled Tool Operators",
        "emp_share": 0.043,
        "wage_share": 0.0372
      },
      {
        "soc": "51-4031",
        "title": "Cutting, Punching, and Press Machine Setters, Operators, and Tenders, Metal and Plastic",
        "emp_share": 0.0402,
        "wage_share": 0.0316
      },
      {
        "soc": "51-9061",
        "title": "Inspectors, Testers, Sorters, Samplers, and Weighers",
        "emp_share": 0.033,
        "wage_share": 0.0279
      },
      {
        "soc": "53-7062",
        "title": "Laborers and Freight, Stock, and Material Movers, Hand",
        "emp_share": 0.0313,
        "wage_share": 0.0217
      },
      {
        "soc": "11-1021",
        "title": "General and Operations Managers",
        "emp_share": 0.0276,
        "wage_share": 0.063
      },
      {
        "soc": "43-5071",
        "title": "Shipping, Receiving, and Inventory Clerks",
        "emp_share": 0.0236,
        "wage_share": 0.0181
      }
    ],
    "quality": "LOW"
  },
  "n_total": {
    "value": 737,
    "source": "SUSB 2022 (firms, all enterprise sizes)",
    "year": "2022",
    "quality": "HIGH"
  },
  "n_band": {
    "value": 198,
    "derivation": "margin 0.1962 (margins.json[33]: Damodaran Jan 2026: Machinery EBITDA/Sales 19.62%); revenue/employee $310,208 (SUSB 2022 receipts/employment at 332216); class <5: 265 firms, avg revenue/firm $488,906 (class receipts/firms), implied EBITDA $95,923 -> out of $1-10M band; class 5-9: 127 firms, avg revenue/firm $1,419,866 (class receipts/firms), implied EBITDA $278,578 -> out of $1-10M band; class 10-19: 121 firms, avg revenue/firm $3,039,314 (class receipts/firms), implied EBITDA $596,313 -> out of $1-10M band; class 20-99: 153 firms, avg revenue/firm $9,339,131 (class receipts/firms), implied EBITDA $1,832,337 -> IN $1-10M band; class 100-499: 45 firms, avg revenue/firm $39,421,267 (class receipts/firms), implied EBITDA $7,734,453 -> IN $1-10M band; class 500+: 26 firms, avg revenue/firm $157,892,769 (class receipts/firms), implied EBITDA $30,978,561 -> out of $1-10M band; n_band = 198",
    "margin_used": 0.1962,
    "margin_source": "Damodaran Jan 2026: Machinery EBITDA/Sales 19.62%",
    "quality": "ESTIMATE"
  },
  "aux": {
    "emp": 25743,
    "payroll_annual": 1541539000,
    "receipts_total": 7985696000,
    "firms_by_size_class": {
      "<5": 265,
      "5-9": 127,
      "10-19": 121,
      "20-99": 153,
      "100-499": 45,
      "500+": 26
    }
  }
}
