{
  "naics": "482112",
  "title": "Short Line Railroads",
  "labor_share": {
    "value": null,
    "method": "SUSB scope excludes this activity, no IPS labor-compensation/output series at any level, and no other receipts source downloaded; labor_share left null (recorded gap).",
    "sources": [],
    "year": "",
    "quality": "ESTIMATE"
  },
  "role_mix": {
    "oews_level": "4-digit 4821",
    "occupations": [
      {
        "soc": "53-4031",
        "title": "Railroad Conductors and Yardmasters",
        "emp_share": 0.1996,
        "wage_share": 0.1901
      },
      {
        "soc": "53-4011",
        "title": "Locomotive Engineers",
        "emp_share": 0.1626,
        "wage_share": 0.1673
      },
      {
        "soc": "47-4061",
        "title": "Rail-Track Laying and Maintenance Equipment Operators",
        "emp_share": 0.0555,
        "wage_share": 0.0475
      },
      {
        "soc": "53-4022",
        "title": "Railroad Brake, Signal, and Switch Operators and Locomotive Firers",
        "emp_share": 0.0525,
        "wage_share": 0.0421
      },
      {
        "soc": "49-3043",
        "title": "Rail Car Repairers",
        "emp_share": 0.0525,
        "wage_share": 0.0474
      },
      {
        "soc": "49-9097",
        "title": "Signal and Track Switch Repairers",
        "emp_share": 0.0314,
        "wage_share": 0.0337
      },
      {
        "soc": "49-1011",
        "title": "First-Line Supervisors of Mechanics, Installers, and Repairers",
        "emp_share": 0.0311,
        "wage_share": 0.0372
      },
      {
        "soc": "53-1047",
        "title": "First-Line Supervisors of Transportation and Material Moving Workers, Except Aircraft Cargo Handling Supervisors",
        "emp_share": 0.0237,
        "wage_share": 0.0289
      },
      {
        "soc": "51-4041",
        "title": "Machinists",
        "emp_share": 0.0218,
        "wage_share": 0.0226
      },
      {
        "soc": "47-1011",
        "title": "First-Line Supervisors of Construction Trades and Extraction Workers",
        "emp_share": 0.0216,
        "wage_share": 0.0267
      }
    ],
    "quality": "MED"
  },
  "n_total": {
    "value": 56,
    "source": "QCEW 2024 private annual avg establishments (SUSB out of scope for this code; establishments are a proxy for firms \u2014 overcounts multi-unit firms)",
    "year": "2024",
    "quality": "LOW"
  },
  "n_band": {
    "value": null,
    "derivation": "margin 0.4919 (margins.json[482]: Damodaran Jan 2026: Transportation (Railroads) EBITDA/Sales 49.19%); revenue/employee $221,674 (SUSB 2022 receipts/employment at 48-49); DATA GAP: no SUSB size-class data for this code; n_band could not be computed \u2014 the research run must supply it with a shown chain, quality ESTIMATE",
    "margin_used": 0.4919,
    "margin_source": "Damodaran Jan 2026: Transportation (Railroads) EBITDA/Sales 49.19%",
    "quality": "ESTIMATE"
  },
  "aux": {
    "emp": 210,
    "payroll_annual": 14177742,
    "receipts_total": 0,
    "firms_by_size_class": {}
  }
}
