{
  "naics": "488410",
  "title": "Motor Vehicle Towing",
  "labor_share": {
    "value": 0.3726,
    "method": "QCEW 2024 private total annual wages at 488410 ($4,120,108,332) x benefits multiplier 1.4294 [ECEC private-industry total comp $46.60/hr / wages $32.60/hr = 1.4294 (March 2026 reference period)] / SUSB 2022 receipts at 488410 ($11,789,387,000). Vintage mismatch: 2024 wages over 2022 receipts, stated. Level: 6-digit. Harmonized to IPS basis \u00f71.3407 (median of 65 dual-method codes).",
    "sources": [
      "BLS QCEW 2024 annual averages (US000, private)",
      "BLS ECEC news release (raw/ecec.nr0.htm)",
      "Census SUSB 2022 (receipts by NAICS)"
    ],
    "year": "2024 wages / 2022 receipts",
    "quality": "MED"
  },
  "role_mix": {
    "oews_level": "4-digit 4884",
    "occupations": [
      {
        "soc": "53-3032",
        "title": "Heavy and Tractor-Trailer Truck Drivers",
        "emp_share": 0.456,
        "wage_share": 0.4677
      },
      {
        "soc": "43-5032",
        "title": "Dispatchers, Except Police, Fire, and Ambulance",
        "emp_share": 0.0748,
        "wage_share": 0.0609
      },
      {
        "soc": "53-7062",
        "title": "Laborers and Freight, Stock, and Material Movers, Hand",
        "emp_share": 0.0477,
        "wage_share": 0.0386
      },
      {
        "soc": "43-9061",
        "title": "Office Clerks, General",
        "emp_share": 0.0425,
        "wage_share": 0.0363
      },
      {
        "soc": "11-1021",
        "title": "General and Operations Managers",
        "emp_share": 0.0378,
        "wage_share": 0.0724
      },
      {
        "soc": "53-7051",
        "title": "Industrial Truck and Tractor Operators",
        "emp_share": 0.0333,
        "wage_share": 0.0304
      },
      {
        "soc": "49-3023",
        "title": "Automotive Service Technicians and Mechanics",
        "emp_share": 0.0308,
        "wage_share": 0.0291
      },
      {
        "soc": "49-3031",
        "title": "Bus and Truck Mechanics and Diesel Engine Specialists",
        "emp_share": 0.0268,
        "wage_share": 0.0295
      },
      {
        "soc": "53-3033",
        "title": "Light Truck Drivers",
        "emp_share": 0.026,
        "wage_share": 0.0227
      },
      {
        "soc": "53-1047",
        "title": "First-Line Supervisors of Transportation and Material Moving Workers, Except Aircraft Cargo Handling Supervisors",
        "emp_share": 0.0259,
        "wage_share": 0.0343
      }
    ],
    "quality": "MED"
  },
  "n_total": {
    "value": 10206,
    "source": "SUSB 2022 (firms, all enterprise sizes)",
    "year": "2022",
    "quality": "HIGH"
  },
  "n_band": {
    "value": 36,
    "derivation": "margin 0.0983 (margins.json[48]: Damodaran Jan 2026: Transportation EBITDA/Sales 9.83%); revenue/employee $168,842 (SUSB 2022 receipts/employment at 488410); class <5: 6,349 firms, avg revenue/firm $363,065 (class receipts/firms), implied EBITDA $35,689 -> out of $1-10M band; class 5-9: 1,875 firms, avg revenue/firm $1,024,905 (class receipts/firms), implied EBITDA $100,748 -> out of $1-10M band; class 10-19: 1,185 firms, avg revenue/firm $2,011,288 (class receipts/firms), implied EBITDA $197,710 -> out of $1-10M band; class 20-99: 761 firms, avg revenue/firm $5,325,903 (class receipts/firms), implied EBITDA $523,536 -> out of $1-10M band; class 100-499: 28 firms, avg revenue/firm $30,945,000 (class receipts/firms), implied EBITDA $3,041,894 -> IN $1-10M band; class 500+: 8 firms, avg revenue/firm $32,467,625 (class receipts/firms), implied EBITDA $3,191,568 -> IN $1-10M band; n_band = 36",
    "margin_used": 0.0983,
    "margin_source": "Damodaran Jan 2026: Transportation EBITDA/Sales 9.83%",
    "quality": "ESTIMATE"
  },
  "aux": {
    "emp": 69825,
    "payroll_annual": 3452241000,
    "receipts_total": 11789387000,
    "firms_by_size_class": {
      "<5": 6349,
      "5-9": 1875,
      "10-19": 1185,
      "20-99": 761,
      "100-499": 28,
      "500+": 8
    }
  }
}
